setup.cfg
setup.py
ariane_docker/__init__.py
ariane_docker/__main__.py
ariane_docker/components.py
ariane_docker/config.py
ariane_docker/connector.py
ariane_docker/docker.py
ariane_docker/exceptions.py
ariane_docker/gears.py
ariane_docker.egg-info/PKG-INFO
ariane_docker.egg-info/SOURCES.txt
ariane_docker.egg-info/dependency_links.txt
ariane_docker.egg-info/requires.txt
ariane_docker.egg-info/top_level.txt
ariane_docker.egg-info/zip-safe