Metadata-Version: 1.1
Name: ariane-docker
Version: 0.1.4b2
Summary: Ariane Plugin Docker
Home-page: https://github.com/echinopsii/net.echinopsii.ariane.community.plugin.docker.git
Author: Mathilde Ffrench
Author-email: mathilde.ffrench@echinopsii.net
License: AGPLv3
Download-URL: https://github.com/echinopsii/net.echinopsii.ariane.community.plugin.docker.git/tarball/0.1.4-b02
Platform: UNKNOWN
Classifier: Development Status :: 4 - Beta
Classifier: Intended Audience :: Developers
Classifier: License :: OSI Approved :: GNU Affero General Public License v3
Classifier: License :: OSI Approved :: GNU Affero General Public License v3 or later (AGPLv3+)
Classifier: Natural Language :: English
Classifier: Operating System :: OS Independent
Classifier: Programming Language :: Python :: 3.4
Classifier: Programming Language :: Python :: Implementation :: CPython
Classifier: Topic :: Communications
Classifier: Topic :: Internet
Classifier: Topic :: Software Development :: Libraries
Classifier: Topic :: Software Development :: Libraries :: Python Modules
Classifier: Topic :: System :: Monitoring
Classifier: Topic :: System :: Networking
